odoo/addons/ddmrp/README.rst
odoo/addons/ddmrp/__init__.py
odoo/addons/ddmrp/__manifest__.py
odoo/addons/ddmrp/data/ir_cron.xml
odoo/addons/ddmrp/data/product_adu_calculation_method_data.xml
odoo/addons/ddmrp/data/stock.buffer.profile.csv
odoo/addons/ddmrp/data/stock_buffer_profile_lead_time_data.xml
odoo/addons/ddmrp/data/stock_buffer_profile_variability_data.xml
odoo/addons/ddmrp/demo/mrp_bom_demo.xml
odoo/addons/ddmrp/demo/product_category_demo.xml
odoo/addons/ddmrp/demo/product_product_demo.xml
odoo/addons/ddmrp/demo/product_supplierinfo_demo.xml
odoo/addons/ddmrp/demo/res_partner_demo.xml
odoo/addons/ddmrp/demo/stock_warehouse_orderpoint_demo.xml
odoo/addons/ddmrp/i18n/ddmrp.pot
odoo/addons/ddmrp/i18n/es.po
odoo/addons/ddmrp/i18n/fr.po
odoo/addons/ddmrp/i18n/zh_Hans.po
odoo/addons/ddmrp/migrations/11.0.1.1.0/pre-migration.py
odoo/addons/ddmrp/migrations/8.0.2.0.0/post-migration.py
odoo/addons/ddmrp/migrations/8.0.2.0.0/pre-migration.py
odoo/addons/ddmrp/models/__init__.py
odoo/addons/ddmrp/models/mrp_bom.py
odoo/addons/ddmrp/models/mrp_production.py
odoo/addons/ddmrp/models/procurement_group.py
odoo/addons/ddmrp/models/procurement_rule.py
odoo/addons/ddmrp/models/product_adu_calculation_method.py
odoo/addons/ddmrp/models/purchase_order.py
odoo/addons/ddmrp/models/stock_buffer_profile.py
odoo/addons/ddmrp/models/stock_buffer_profile_lead_time.py
odoo/addons/ddmrp/models/stock_buffer_profile_variability.py
odoo/addons/ddmrp/models/stock_warehouse.py
odoo/addons/ddmrp/models/stock_warehouse_orderpoint.py
odoo/addons/ddmrp/readme/CONFIGURE.rst
odoo/addons/ddmrp/readme/CONTRIBUTORS.rst
odoo/addons/ddmrp/readme/CREDITS.rst
odoo/addons/ddmrp/readme/DESCRIPTION.rst
odoo/addons/ddmrp/readme/HISTORY.rst
odoo/addons/ddmrp/readme/INSTALL.rst
odoo/addons/ddmrp/readme/ROADMAP.rst
odoo/addons/ddmrp/readme/USAGE.rst
odoo/addons/ddmrp/report/__init__.py
odoo/addons/ddmrp/report/bom_structure.py
odoo11_addon_ddmrp-11.0.1.3.2.dist-info/METADATA
odoo11_addon_ddmrp-11.0.1.3.2.dist-info/RECORD
odoo11_addon_ddmrp-11.0.1.3.2.dist-info/WHEEL
odoo11_addon_ddmrp-11.0.1.3.2.dist-info/top_level.txt
