Metadata-Version: 2.1
Name: odoo11-addon-ddmrp
Version: 11.0.1.3.2
Summary: Demand Driven Material Requirements Planning
Home-page: https://github.com/OCA/ddmrp
Author: Eficent, Odoo Community Association (OCA)
Author-email: support@odoo-community.org
License: AGPL-3
Platform: UNKNOWN
Classifier: Programming Language :: Python
Classifier: Framework :: Odoo
Classifier: License :: OSI Approved :: GNU Affero General Public License v3
Classifier: Development Status :: 4 - Beta
Requires-Python: >=2.7, !=3.0.*, !=3.1.*, !=3.2.*, !=3.3.*, !=3.4.*
Requires-Dist: odoo11-addon-base-cron-exclusion
Requires-Dist: odoo11-addon-mrp-bom-location
Requires-Dist: odoo11-addon-mrp-multi-level
Requires-Dist: odoo11-addon-stock-available-unreserved
Requires-Dist: odoo11-addon-stock-demand-estimate
Requires-Dist: odoo11-addon-stock-orderpoint-manual-procurement
Requires-Dist: odoo11-addon-stock-orderpoint-purchase-link
Requires-Dist: odoo11-addon-stock-orderpoint-uom
Requires-Dist: odoo11-addon-stock-warehouse-calendar
Requires-Dist: odoo11-addon-stock-warehouse-orderpoint-stock-info
Requires-Dist: odoo11-addon-stock-warehouse-orderpoint-stock-info-unreserved
Requires-Dist: odoo11-addon-web-tree-dynamic-colored-field
Requires-Dist: odoo11-addon-web-widget-bokeh-chart
Requires-Dist: odoo (<11.1dev,>=11.0a)
